dilipred/__init__.py
dilipred/constants.py
dilipred/features/all_features_desc.csv
dilipred/features/features_morgan_mordred_maccs_physc.txt
dilipred/main.py
dilipred/models/bestlivmodel_10_model.sav
dilipred/models/bestlivmodel_11_model.sav
dilipred/models/bestlivmodel_14_model.sav
dilipred/models/bestlivmodel_15_model.sav
dilipred/models/bestlivmodel_16_model.sav
dilipred/models/bestlivmodel_3_model.sav
dilipred/models/bestlivmodel_5_model.sav
dilipred/models/bestlivmodel_6_model.sav
dilipred/models/bestlivmodel_7_model.sav
dilipred/models/bestlivmodel_8_model.sav
dilipred/models/bestlivmodel_median pMolar total plasma concentration_model.sav
dilipred/models/bestlivmodel_median pMolar unbound plasma concentration_model.sav
dilipred/models/final_dili_model.sav
dilipred-4.0.9.dist-info/METADATA
dilipred-4.0.9.dist-info/WHEEL
dilipred-4.0.9.dist-info/entry_points.txt
dilipred-4.0.9.dist-info/RECORD
